httper.py
httper-0.0.1.dist-info/METADATA
httper-0.0.1.dist-info/WHEEL
httper-0.0.1.dist-info/entry_points.txt
httper-0.0.1.dist-info/top_level.txt
httper-0.0.1.dist-info/RECORD
