Metadata-Version: 2.1
Name: httper
Version: 0.0.1
Summary: http请求工具
Home-page: https://github.com/kancyframework/python-plugins/tree/main/httper
Author: kancy
Author-email: 793272861@qq.com
License: MIT
Platform: UNKNOWN
Classifier: License :: OSI Approved :: MIT License
Classifier: Programming Language :: Python
Classifier: Programming Language :: Python :: 3
Classifier: Programming Language :: Python :: 3.6
Classifier: Programming Language :: Python :: Implementation :: CPython
Classifier: Programming Language :: Python :: Implementation :: PyPy
Requires-Python: >=3
Requires-Dist: requests
Provides-Extra: tqdm_feature
Requires-Dist: tqdm ; extra == 'tqdm_feature'
